mbget/__init__.py
mbget/barrel_asset.py
mbget/cache.py
mbget/config.py
mbget/dependency.py
mbget/errors.py
mbget/file_hasher.py
mbget/github_downloader.py
mbget/main.py
mbget/manifest.py
mbget/packages.py
mbget/project.py
mbget/update.py
mbget/version.py
mbpkg-1.4.1.dist-info/LICENCE
mbpkg-1.4.1.dist-info/METADATA
mbpkg-1.4.1.dist-info/WHEEL
mbpkg-1.4.1.dist-info/entry_points.txt
mbpkg-1.4.1.dist-info/top_level.txt
mbpkg-1.4.1.dist-info/RECORD
