Metadata-Version: 2.1
Name: mbpkg
Version: 1.4.1
Summary: Connect IQ Package Manager
Home-page: https://github.com/gcaufield/MonkeyPack
Author: Greg Caufield
Author-email: greg@embeddedcoffee.ca
License: MIT
Project-URL: Source, https://github.com/gcaufield/MonkeyPack.git
Project-URL: Tracker, https://github.com/gcaufield/MonkeyPack/issues
Keywords: garmin connectiq packages
Platform: UNKNOWN
Classifier: Development Status :: 4 - Beta
Classifier: Intended Audience :: Developers
Classifier: Natural Language :: English
Classifier: License :: OSI Approved :: MIT License
Classifier: Programming Language :: Python :: 3
Classifier: Programming Language :: Python :: 3.6
Classifier: Programming Language :: Python :: 3.7
Classifier: Programming Language :: Python :: 3.8
Requires-Python: >=3.6.*, < 4
Requires-Dist: requests (<3,>=2.0)
Requires-Dist: PyGithub (~=1.53)
